{
  "articles": [
    {
      "id": "20260312-IN-001",
      "title": "[1] 5G 通信领域快速发展，SMT 设备需求持续增长",
      "date": "2026-03-12",
      "category": "行业资讯",
      "summary": "随着 5G 通信的快速发展，SMT 设备市场需求持续增长。本文分析当前市场趋势和发展机遇，为行业提供参考。",
      "content": "随着电子制造行业的快速发展，SMT 设备作为核心装备，其技术水平和性能指标直接影响生产效率和产品质量...",
      "link": "/news/industry/20260312-IN-001.html",
      "author": "仝志伟业",
      "views": 0,
      "tags": ["SMT 设备", "5G 通信", "行业趋势"]
    },
    {
      "id": "20260312-IN-002",
      "title": "[2] 2026 年新能源汽车市场趋势分析：点胶机迎来新机遇",
      "date": "2026-03-12",
      "category": "行业资讯",
      "summary": "最新数据显示，新能源汽车产业规模不断扩大，点胶机作为核心装备，将迎来重要发展机遇。",
      "link": "/news/industry/20260312-IN-002.html",
      "author": "仝志伟业",
      "views": 0,
      "tags": ["点胶机", "新能源汽车", "市场分析"]
    },
    {
      "id": "20260312-TD-001",
      "title": "[1] 高精度点胶机工艺优化方案详解",
      "date": "2026-03-12",
      "category": "技术动态",
      "summary": "本文详细介绍高精度点胶机的工艺优化方案，包括关键技术要点、实施步骤和注意事项，为工程师提供参考。",
      "link": "/news/technology/20260312-TD-001.html",
      "author": "仝志伟业",
      "views": 0,
      "tags": ["点胶机", "工艺优化", "技术"]
    },
    {
      "id": "20260312-TD-002",
      "title": "[2] 如何提升锡膏印刷机的印刷质量？",
      "date": "2026-03-12",
      "category": "技术动态",
      "summary": "针对锡膏印刷机应用中的常见问题，本文提供系统的质量控制方法，帮助提升生产效率和产品质量。",
      "link": "/news/technology/20260312-TD-002.html",
      "author": "仝志伟业",
      "views": 0,
      "tags": ["锡膏印刷机", "质量控制", "技术"]
    }
  ],
  "lastUpdate": "2026-03-12T22:45:00+08:00",
  "updateSchedule": "每天 9:00 自动更新"
}
